oschart/__init__.py
oschart/api/__init__.py
oschart/api/charts_data.py
oschart/api/post_data.py
oschart/database/__init__.py
oschart/database/database.py
oschart/utils/__init__.py
oschart/utils/chart_utils.py
oschart/utils/constant.py
oschart/utils/field_info.py
oschart/utils/os_error.py
test/__init__.py
test/os_chart_test.py
os_charts-0.3.2.dist-info/LICENSE
os_charts-0.3.2.dist-info/METADATA
os_charts-0.3.2.dist-info/WHEEL
os_charts-0.3.2.dist-info/top_level.txt
os_charts-0.3.2.dist-info/RECORD
