Metadata-Version: 2.1
Name: os-charts
Version: 0.3.2
Summary: ## OsCharts  > OS 相关的指标计算库   ## 入口文件  ``` oschart -> charts_data.py ```  ## 使用  #### 安装依赖包  1. 配置数据源  ```bash pass ```  2. 调用  ```bash pass ``` 
Home-page: UNKNOWN
Author: LiuFeng
Author-email: yuyu62488@gmail.com
License: UNKNOWN
Platform: UNKNOWN
Classifier: Programming Language :: Python :: 3
Classifier: License :: OSI Approved :: MIT License
Classifier: Operating System :: OS Independent
Requires-Python: >=3
Requires-Dist: DBUtils>=2.0
Requires-Dist: elasticsearch>=7.1.0
Requires-Dist: PyMySQL>=0.9.3
